goonlang/__init__.py
goonlang/__main__.py
goonlang/importer.py
goonlang/parent.py
goonlang/parser.py
goonlang/runner.py
goonlang/grammar/goonlang.lark
goonlang-25.2.23.dist-info/LICENSE.txt
goonlang-25.2.23.dist-info/METADATA
goonlang-25.2.23.dist-info/WHEEL
goonlang-25.2.23.dist-info/entry_points.txt
goonlang-25.2.23.dist-info/top_level.txt
goonlang-25.2.23.dist-info/RECORD
